custombox/__init__.py
custombox/custombox.py
custombox-0.1.3.dist-info/METADATA
custombox-0.1.3.dist-info/WHEEL
custombox-0.1.3.dist-info/top_level.txt
custombox-0.1.3.dist-info/RECORD
