Metadata-Version: 2.4
Name: custombox
Version: 0.1.3
Summary: Custom tkinter dialog box with flexible buttons and commands
Home-page: 
Author: Kiavash Nourafshan
Author-email: kianour9@gmail.com
Classifier: Programming Language :: Python :: 3
Classifier: Operating System :: OS Independent
Requires-Python: >=3.6
Dynamic: author
Dynamic: author-email
Dynamic: classifier
Dynamic: description
Dynamic: description-content-type
Dynamic: requires-python
Dynamic: summary
